[
    {
      "name": "John Doe",
      "age": 28,
      "phone": "123-456-7890"
    },
    {
      "name": "Jane Smith",
      "age": 34,
      "phone": "987-654-3210"
    },
    {
      "name": "Alice Johnson",
      "age": 25,
      "phone": "555-123-4567"
    },
    {
      "name": "Bob Brown",
      "age": 40,
      "phone": "444-789-0123"
    },
    {
      "name": "Charlie Wilson",
      "age": 22,
      "phone": "333-567-8901"
    },
    {
      "name": "David Lee",
      "age": 30,
      "phone": "222-345-6789"
    },
    {
      "name": "Emma Thomas",
      "age": 27,
      "phone": "111-234-5678"
    },
    {
      "name": "Frank White",
      "age": 35,
      "phone": "666-789-1234"
    },
    {
      "name": "Grace Harris",
      "age": 29,
      "phone": "777-890-2345"
    },
    {
      "name": "Henry Martin",
      "age": 31,
      "phone": "888-901-3456"
    }
  ]
  